<?xml version = '1.0' encoding = 'UTF-8'?>
<FKIndexAssociation class="oracle.dbtools.crest.model.design.relational.FKIndexAssociation" directorySegmentName="seg_2" id="ED942056-F21C-7D1B-3D9D-B4F5DEC49499" containerWithKeyObject="E1EFB3F5-FBEA-679B-27B8-984D0FF0A14B" localFKIndex="A867EE31-C9D0-7BCE-FED3-C4E9582029AE" name="TKR_ESPEC_ALIADO_SUBESPEC_FK">
<sourceConnName>TEKER_PROD</sourceConnName>
<sourceObjSchema>TEKER_PROD</sourceObjSchema>
<sourceObjName>TKR_ESPEC_ALIADO_SUBESPEC_FK</sourceObjName>
<createdBy>JoshuaOrtizG</createdBy>
<createdTime>2026-05-12 20:11:58 UTC</createdTime>
<ownerDesignName>Modelo_Relacional_Citas</ownerDesignName>
<referredTableLongName>TEKER_PROD.TKR_SUBESPECIALIDADES</referredTableLongName>
<deleteRule>NO ACTION</deleteRule>
<referredTableID>41DD7D98-29D4-3369-F452-020BB5BA0E4D</referredTableID>
<keyObject>E2FB28A1-04D3-7BD6-3AD5-7AE581FB9D41</keyObject>
<referredKeyID>E2FB28A1-04D3-7BD6-3AD5-7AE581FB9D41</referredKeyID>
<mandatory>false</mandatory>
<refColNames>ID</refColNames>
<transferable>true</transferable>
<rely>false</rely>
<columnDependencyConstraintGenerateInDDL>true</columnDependencyConstraintGenerateInDDL>
</FKIndexAssociation>